LICENSE
README.txt
setup.py
ulab_image_contrast/__init__.py
ulab_image_contrast.egg-info/PKG-INFO
ulab_image_contrast.egg-info/SOURCES.txt
ulab_image_contrast.egg-info/dependency_links.txt
ulab_image_contrast.egg-info/entry_points.txt
ulab_image_contrast.egg-info/requires.txt
ulab_image_contrast.egg-info/top_level.txt
ulab_image_contrast/command/__init__.py
ulab_image_contrast/command/command_contrast.py
ulab_image_contrast/command/command_help.py
ulab_image_contrast/command/common.py
ulab_image_contrast/command/console_master.py
ulab_image_contrast/core/__init__.py
ulab_image_contrast/core/ssim.py