Metadata-Version: 2.1
Name: ulab-image-contrast
Version: 0.0.1.dev1
Summary: contrast image
Home-page: UNKNOWN
Author: 17RADIX
Author-email: 17raidx@gmail.com
License: MIT License
Platform: UNKNOWN
Classifier: Programming Language :: Python :: 3
Classifier: License :: OSI Approved :: MIT License
Classifier: Operating System :: OS Independent
License-File: LICENSE
